scinet/__init__.py
scinet/core.py
scinet/core/__init__.py
scinet/core/graph.py
scinet/core/network.py
scinet/utils/__init__.py
scinet/utils/profiler.py
tests/__init__.py
tests/test_graph.py
tests/test_network.py
scinet_JoshGoA-0.4.9.dist-info/LICENSE.md
scinet_JoshGoA-0.4.9.dist-info/METADATA
scinet_JoshGoA-0.4.9.dist-info/WHEEL
scinet_JoshGoA-0.4.9.dist-info/top_level.txt
scinet_JoshGoA-0.4.9.dist-info/RECORD
