Metadata-Version: 2.1
Name: scinet-JoshGoA
Version: 0.4.9
Summary: Network science abstract data types
Home-page: https://github.com/JoshGoA/scinet.git
Author: JoshGoA
License: UNKNOWN
Platform: UNKNOWN
Classifier: Programming Language :: Python :: 3
Classifier: License :: OSI Approved :: MIT License
Classifier: Operating System :: OS Independent
Requires-Python: >=3.8
